sqltills/__init__.py
sqltills/crud.py
sqltills/datastructures.py
sqltills/parsetree.py
SQLtills-0.0.3.dist-info/LICENSE.md
SQLtills-0.0.3.dist-info/METADATA
SQLtills-0.0.3.dist-info/WHEEL
SQLtills-0.0.3.dist-info/top_level.txt
SQLtills-0.0.3.dist-info/RECORD
