Metadata-Version: 2.1
Name: SQLtills
Version: 0.0.3
Summary: Simple CRUD utilities for sqlalchemy
Home-page: https://github.com/Moro-Code/sqltills
Author: Omar Nasr
Author-email: omardev9898@gmail.com
License: MIT
Platform: UNKNOWN
Classifier: Programming Language :: Python :: 3.7
Classifier: License :: OSI Approved :: MIT License
Classifier: Operating System :: OS Independent
Classifier: Intended Audience :: Developers
Requires-Dist: SQLAlchemy (==1.3)
